README.md
__init__.py
__main__.py
command.py
functions.py
load.py
out.py
watchrun.py
x5.egg-info/PKG-INFO
x5.egg-info/SOURCES.txt
x5.egg-info/dependency_links.txt
x5.egg-info/entry_points.txt
x5.egg-info/requires.txt
x5.egg-info/top_level.txt
x5-1.0.0.dist-info/LICENSE
x5-1.0.0.dist-info/METADATA
x5-1.0.0.dist-info/WHEEL
x5-1.0.0.dist-info/entry_points.txt
x5-1.0.0.dist-info/top_level.txt
x5-1.0.0.dist-info/RECORD
